{"hash":"0bcb33e2bdf72eba56032b8d238984aede4c8337","data":{"doc":{"title":"Project configuration","headings":[{"value":"Project configuration"}],"subtitles":[{"depth":1,"value":"Project configuration","anchor":"#project-configuration"},{"depth":2,"value":"siteName","anchor":"#sitename"},{"depth":2,"value":"siteDescription","anchor":"#sitedescription"},{"depth":2,"value":"siteUrl","anchor":"#siteurl"},{"depth":2,"value":"pathPrefix","anchor":"#pathprefix"},{"depth":2,"value":"titleTemplate","anchor":"#titletemplate"},{"depth":2,"value":"plugins","anchor":"#plugins"},{"depth":2,"value":"templates","anchor":"#templates"},{"depth":2,"value":"metadata","anchor":"#metadata"},{"depth":2,"value":"icon","anchor":"#icon"},{"depth":2,"value":"configureWebpack","anchor":"#configurewebpack"},{"depth":2,"value":"chainWebpack","anchor":"#chainwebpack"},{"depth":2,"value":"runtimeCompiler","anchor":"#runtimecompiler"},{"depth":2,"value":"configureServer","anchor":"#configureserver"},{"depth":2,"value":"permalinks.trailingSlash","anchor":"#permalinkstrailingslash"},{"depth":2,"value":"permalinks.slugify","anchor":"#permalinksslugify"},{"depth":2,"value":"css.split","anchor":"#csssplit"},{"depth":2,"value":"css.loaderOptions","anchor":"#cssloaderoptions"},{"depth":2,"value":"host","anchor":"#host"},{"depth":2,"value":"port","anchor":"#port"},{"depth":2,"value":"outputDir","anchor":"#outputdir"}]}},"context":{}}